{
  "type": "minecraft:block",
  "pools": [
    {
      "rolls": 1.0,
      "entries": [
        {
          "type": "minecraft:item",
          "conditions": [
            {
              "block": "minecraft:cocoa",
              "condition": "minecraft:block_state_property",
              "properties": {
                "age": "2"
              }
            },
            {
              "condition": "minecraft:match_tool",
              "predicate": {
                "tag": "createchocolatefactory:machete_like"
              }
            }
          ],
          "name": "createchocolatefactory:cocoa_block_closed"
        }
      ]
    }
  ],
  "random_sequence": "minecraft:blocks/cocoa"
}